acrm/__init__.py
acrm/__version__.py
acrm/application.py
acrm/commands/__init__.py
acrm/commands/_base.py
acrm/commands/add.py
acrm/commands/dl.py
acrm/commands/ls.py
acrm/commands/rm.py
acrm-0.1.3.dist-info/licenses/LICENSE
acrm-0.1.3.dist-info/METADATA
acrm-0.1.3.dist-info/WHEEL
acrm-0.1.3.dist-info/entry_points.txt
acrm-0.1.3.dist-info/top_level.txt
acrm-0.1.3.dist-info/RECORD
