Metadata-Version: 2.4
Name: acrm
Version: 0.1.3
Summary: An Arch Linux custom repository manager
Author-email: mistiru <dev@mistiru.me>
License-Expression: MIT
Project-URL: source, https://github.com/mistiru/acrm
Classifier: Programming Language :: Python :: 3
Classifier: Programming Language :: Python :: 3.11
Classifier: Programming Language :: Python :: 3.12
Classifier: Programming Language :: Python :: 3.13
Requires-Python: >=3.11
License-File: LICENSE
Requires-Dist: cleo~=2.0
Dynamic: license-file
